{
  "name": "Feather RP2040",
  "manufacturer": "Adafruit",
  "cpu": "RP2040",
  "cpuArchitecture": "ARM Cortex-M0",
  "cpuSpeed": "125MHZ",
  "flash": "8MB",
  "price": 11.95,
  "dimensions": {
    "length": 51,
    "width": 23,
    "height": 1
  },
  "gpio": 21,
  "analog": 4,
  "usbConnectorType": "Type-C",
  "wifi": false,
  "bluetooth": false,
  "lora": false,
  "ethernet": false,
  "zigbee": false,
  "can": false,
  "matter": false,
  "accelerometer": false,
  "gyroscope": false,
  "temperatureSensor": false,
  "hallSensor": false,
  "lightSensor": false,
  "altitudeSensor": false,
  "motionSensor": false,
  "batteryPowered": false,
  "liPoCharging": true,
  "ultraLowPower": false,
  "lowPowerDeepSleep": false,
  "barrelJack5V": false,
  "poe": false,
  "camera": false,
  "display": false,
  "touchScreen": false,
  "sdCard": false,
  "openSource": true,
  "breadBoardFriendly": false,
  "rtc": false,
  "i2c": true,
  "spi": true,
  "nativeUSB": false,
  "usbHost": false,
  "stemmaConnector": true,
  "groveConnector": false,
  "uextConnector": false,
  "productUrl": "https://www.amazon.com/Adafruit-Feather-RP2040-Ada-4884/dp/B0929FSTVR?crid=22LFMSCA0BGG3&keywords=Adafruit+Feather+RP2040&qid=1701741314&sprefix=adafruit+feather+rp2040%2Caps%2C97&sr=8-3&linkCode=ll1&tag=smartbeedes07-20&linkId=15255bbec49dbae8732eeebc0c8a9cbc&language=en_US&ref_=as_li_ss_tl",
  "schematicUrl": "https://learn.adafruit.com/assets/116896",
  "githubUrl": "https://github.com/adafruit/Adafruit-Feather-RP2040-PCB",
  "imageUrl": "https://firebasestorage.googleapis.com/v0/b/microcontrollerdb.appspot.com/o/images%2Fboards%2FNfz6hiDyS14bQdnUGlvNY?alt=media&token=22338c69-3408-4cf1-9bf5-43274b1d06b7",
  "id": "adafruit-feather-rp2040",
  "brand": "adafruit-feather-rp2040",
  "threadProtocol": false,
  "batteryConnector": false,
  "batteryMonitoring": false,
  "dualLDOs": false,
  "pioUSB": false,
  "usbDetection": false,
  "dualUSB": false,
  "hid": false,
  "speaker": false,
  "microphone": false,
  "solarCharging": false
}